.travis.yml
AUTHORS
ChangeLog
LICENSE
README.md
requirements.txt
setup.cfg
setup.py
test-requirements.txt
tox.ini
test/__init__.py
test/test_ubersmith_object_api.py
ub_object_client/client.py
ub_object_client/ubersmith_object_api.py
ub_object_client.egg-info/PKG-INFO
ub_object_client.egg-info/SOURCES.txt
ub_object_client.egg-info/dependency_links.txt
ub_object_client.egg-info/not-zip-safe
ub_object_client.egg-info/pbr.json
ub_object_client.egg-info/requires.txt
ub_object_client.egg-info/top_level.txt