Metadata-Version: 1.1
Name: ub-object-client
Version: 0.0.2
Summary: Object based python client for Übersmith
Home-page: https://github.com/internap/ub-object-client
Author: Internap
Author-email: opensource@internap.com
License: UNKNOWN
Platform: UNKNOWN
Classifier: Development Status :: 5 - Production/Stable
Classifier: Intended Audience :: Developers
Classifier: License :: OSI Approved :: Apache Software License
Classifier: Operating System :: POSIX
Classifier: Programming Language :: Python :: 3.4
